MANIFEST.in
setup.cfg
setup.py
vLabtool/I2C_class.py
vLabtool/MCP4728_class.py
vLabtool/NRF24L01_class.py
vLabtool/NRF_NODE.py
vLabtool/SPI_class.py
vLabtool/__init__.py
vLabtool/achan.py
vLabtool/calibrate_bipolars.py
vLabtool/commands_proto.py
vLabtool/custom_widgets.py
vLabtool/customui_rc.py
vLabtool/digital_channel.py
vLabtool/experiment.py
vLabtool/experiment_standalone.py
vLabtool/iPythonEmbed.py
vLabtool/interface.py
vLabtool/packet_handler.py
vLabtool/sensorlist.py
vLabtool/template_scope.py
vLabtool.egg-info/PKG-INFO
vLabtool.egg-info/SOURCES.txt
vLabtool.egg-info/dependency_links.txt
vLabtool.egg-info/requires.txt
vLabtool.egg-info/top_level.txt
vLabtool/SENSORS/BMP180.py
vLabtool/SENSORS/ComplementaryFilter.py
vLabtool/SENSORS/HMC5883L.py
vLabtool/SENSORS/Kalman.py
vLabtool/SENSORS/MLX90614.py
vLabtool/SENSORS/MPU6050.py
vLabtool/SENSORS/SHT21.py
vLabtool/SENSORS/TSL2561.py
vLabtool/SENSORS/__init__.py
vLabtool/bin/vLabtool-AccelerometerDemo
vLabtool/bin/vLabtool-bodePlots
vLabtool/bin/vLabtool-console
vLabtool/bin/vLabtool-diodeIV
vLabtool/bin/vLabtool-experiments
vLabtool/bin/vLabtool-scope
vLabtool/bin/vLabtool-sensorDemo
vLabtool/bin/vLabtool-stream
vLabtool/bin/vLabtool-transientRLC
vLabtool/bin/vLabtool-transistorCE
vLabtool/bin/vLabtool-wirelessDemo
vLabtool/calib_data/__init__.py
vLabtool/calib_data/bcalib.py
vLabtool/calib_data/proto.rules
vLabtool/docs/docs/Apps.rst
vLabtool/docs/docs/I2C_class.rst
vLabtool/docs/docs/Makefile
vLabtool/docs/docs/NRF24L01_class.rst
vLabtool/docs/docs/NRF_NODE.rst
vLabtool/docs/docs/SPI_class.rst
vLabtool/docs/docs/conf.py
vLabtool/docs/docs/customui_rc.rst
vLabtool/docs/docs/experiment.rst
vLabtool/docs/docs/index.rst
vLabtool/docs/docs/interface.rst
vLabtool/docs/docs/make.bat
vLabtool/docs/docs/_build/doctrees/Apps.doctree
vLabtool/docs/docs/_build/doctrees/I2C_class.doctree
vLabtool/docs/docs/_build/doctrees/NRF24L01_class.doctree
vLabtool/docs/docs/_build/doctrees/NRF_NODE.doctree
vLabtool/docs/docs/_build/doctrees/SPI_class.doctree
vLabtool/docs/docs/_build/doctrees/customui_rc.doctree
vLabtool/docs/docs/_build/doctrees/environment.pickle
