Metadata-Version: 1.0
Name: vLabtool
Version: 1.0
Summary: Package to deal with vLabtool
Home-page: https://hackaday.io/project/6490
Author: Jithin B.P.
Author-email: jithinbp@gmail.com
License: UNKNOWN
Platform: UNKNOWN
